Guia9/Ex5/Exemplo_0905.v
// ---------------------------
// -- test clock generator (2)
// ---------------------------
module clock ( output clk );
reg clk;
initial
begin
clk = 1'b0;
end
always
begin
#33 clk = ~clk;
end
endmodule
module pulse ( signal, clock );
input clock;
output signal;
reg signal;
always @ ( clock )
begin
signal = 1'b1;
#3 signal = 1'b0;
#3 signal = 1'b1;
#3 signal = 1'b0;
end
endmodule // pulse
module trigger ( signal, on, clock );
input on, clock;
output signal;
reg signal;
always @ ( posedge clock & on )
begin
#60 signal = 1'b1;
#60 signal = 1'b0;
end
endmodule // trigger
module Exemplo_0902;
wire clock;
clock clk ( clock );
reg p;
wire p1,t1;
pulse pulse1 ( p1, clock );
trigger trigger1 ( t1, p, clock );
initial begin
p = 1'b0;
end
initial begin
$dumpfile ( "Exemplo0902.vcd" );
$dumpvars ( 1, clock, p1, p, t1 );
#060 p = 1'b1;
#120 p = 1'b0;
#180 p = 1'b1;
#240 p = 1'b0;
#300 p = 1'b1;
#360 p = 1'b0;
#376 $finish;
end
endmodule // Exemplo_0902

Guia9/Ex5/Exemplo0902.vcd
$date
	Thu Oct  8 20:03:01 2020
$end
$version
	Icarus Verilog
$end
$timescale
	1s
$end
$scope module Exemplo_0902 $end
$var wire 1 ! clock $end
$upscope $end
$scope module Exemplo_0902 $end
$var wire 1 " p1 $end
$upscope $end
$scope module Exemplo_0902 $end
$var reg 1 # p $end
$upscope $end
$scope module Exemplo_0902 $end
$var wire 1 $ t1 $end
$upscope $end
$enddefinitions $end
#0
$dumpvars
x$
0#
1"
0!
$end
#3
0"
#6
1"
#9
0"
#33
1"
1!
#36
0"
#39
1"
#42
0"
#60
1#
#66
1"
0!
#69
0"
#72
1"
#75
0"
#99
1"
1!
#102
0"
#105
1"
#108
0"
#120
1$
#132
1"
0!
#135
0"
#138
1"
#141
0"
#165
1"
1!
#168
0"
#171
1"
#174
0"
#180
0$
0#
#198
1"
0!
#201
0"
#204
1"
#207
0"
#231
1"
1!
#234
0"
#237
1"
#240
0"
#264
1"
0!
#267
0"
#270
1"
#273
0"
#297
1"
1!
#300
0"
#303
1"
#306
0"
#330
1"
0!
#333
0"
#336
1"
#339
0"
#360
1#
#363
1"
1!
#366
0"
#369
1"
#372
0"
#396
1"
0!
#399
0"
#402
1"
#405
0"
#423
1$
#429
1"
1!
#432
0"
#435
1"
#438
0"
#462
1"
0!
#465
0"
#468
1"
#471
0"
#483
0$
#495
1"
1!
#498
0"
#501
1"
#504
0"
#528
1"
0!
#531
0"
#534
1"
#537
0"
#555
1$
#561
1"
1!
#564
0"
#567
1"
#570
0"
#594
1"
0!
#597
0"
#600
1"
0#
#603
0"
#615
0$
#627
1"
1!
#630
0"
#633
1"
#636
0"
#660
1"
0!
#663
0"
#666
1"
#669
0"
#693
1"
1!
#696
0"
#699
1"
#702
0"
#726
1"
0!
#729
0"
#732
1"
#735
0"
#759
1"
1!
#762
0"
#765
1"
#768
0"
#792
1"
0!
#795
0"
#798
1"
#801
0"
#825
1"
1!
#828
0"
#831
1"
#834
0"
#858
1"
0!
#861
0"
#864
1"
#867
0"
#891
1"
1!
#894
0"
#897
1"
#900
0"
1#
#924
1"
0!
#927
0"
#930
1"
#933
0"
#957
1"
1!
#960
0"
1$
#963
1"
#966
0"
#990
1"
0!
#993
0"
#996
1"
#999
0"
#1020
0$
#1023
1"
1!
#1026
0"
#1029
1"
#1032
0"
#1056
1"
0!
#1059
0"
#1062
1"
#1065
0"
#1083
1$
#1089
1"
1!
#1092
0"
#1095
1"
#1098
0"
#1122
1"
0!
#1125
0"
#1128
1"
#1131
0"
#1143
0$
#1155
1"
1!
#1158
0"
#1161
1"
#1164
0"
#1188
1"
0!
#1191
0"
#1194
1"
#1197
0"
#1215
1$
#1221
1"
1!
#1224
0"
#1227
1"
#1230
0"
#1254
1"
0!
#1257
0"
#1260
1"
0#
#1263
0"
#1275
0$
#1287
1"
1!
#1290
0"
#1293
1"
#1296
0"
#1320
1"
0!
#1323
0"
#1326
1"
#1329
0"
#1353
1"
1!
#1356
0"
#1359
1"
#1362
0"
#1386
1"
0!
#1389
0"
#1392
1"
#1395
0"
#1419
1"
1!
#1422
0"
#1425
1"
#1428
0"
#1452
1"
0!
#1455
0"
#1458
1"
#1461
0"
#1485
1"
1!
#1488
0"
#1491
1"
#1494
0"
#1518
1"
0!
#1521
0"
#1524
1"
#1527
0"
#1551
1"
1!
#1554
0"
#1557
1"
#1560
0"
#1584
1"
0!
#1587
0"
#1590
1"
#1593
0"
#1617
1"
1!
#1620
0"
#1623
1"
#1626
0"
